cognitive_kernel/__init__.py
cognitive_kernel/cognitive_modes.py
cognitive_kernel/core.py
cognitive_kernel/pipeline.py
cognitive_kernel/vector_integration.py
cognitive_kernel/engines/__init__.py
cognitive_kernel/engines/interfaces.py
cognitive_kernel/engines/amygdala/__init__.py
cognitive_kernel/engines/amygdala/amygdala_engine.py
cognitive_kernel/engines/amygdala/config.py
cognitive_kernel/engines/amygdala/data_types.py
cognitive_kernel/engines/amygdala/fear_learning.py
cognitive_kernel/engines/basal_ganglia/__init__.py
cognitive_kernel/engines/basal_ganglia/basal_ganglia_engine.py
cognitive_kernel/engines/basal_ganglia/config.py
cognitive_kernel/engines/basal_ganglia/data_types.py
cognitive_kernel/engines/dynamics/__init__.py
cognitive_kernel/engines/dynamics/config.py
cognitive_kernel/engines/dynamics/dynamics_engine.py
cognitive_kernel/engines/dynamics/models.py
cognitive_kernel/engines/hypothalamus/__init__.py
cognitive_kernel/engines/hypothalamus/config.py
cognitive_kernel/engines/hypothalamus/data_types.py
cognitive_kernel/engines/hypothalamus/hpa_dynamics.py
cognitive_kernel/engines/hypothalamus/hypothalamus_engine.py
cognitive_kernel/engines/memoryrank/__init__.py
cognitive_kernel/engines/memoryrank/config.py
cognitive_kernel/engines/memoryrank/memoryrank_engine.py
cognitive_kernel/engines/memoryrank/persistence.py
cognitive_kernel/engines/memoryrank/pham_chain_persistence.json
cognitive_kernel/engines/panorama/__init__.py
cognitive_kernel/engines/panorama/config.py
cognitive_kernel/engines/panorama/panorama_engine.py
cognitive_kernel/engines/panorama/persistence.py
cognitive_kernel/engines/panorama/pham_chain_persistence.json
cognitive_kernel/engines/pfc/__init__.py
cognitive_kernel/engines/pfc/config.py
cognitive_kernel/engines/pfc/models.py
cognitive_kernel/engines/pfc/pfc_engine.py
cognitive_kernel/engines/thalamus/__init__.py
cognitive_kernel/engines/thalamus/config.py
cognitive_kernel/engines/thalamus/data_types.py
cognitive_kernel-2.0.2.dist-info/licenses/LICENSE
cognitive_kernel-2.0.2.dist-info/METADATA
cognitive_kernel-2.0.2.dist-info/WHEEL
cognitive_kernel-2.0.2.dist-info/top_level.txt
cognitive_kernel-2.0.2.dist-info/RECORD
