Metadata-Version: 2.4
Name: cognitive-kernel
Version: 2.0.2
Summary: Minimal, verifiable implementation of persistent long-term memory for AI agents
Author-email: "GNJz (Qquarts)" <qquartsco@gmail.com>
Maintainer-email: "GNJz (Qquarts)" <qquartsco@gmail.com>
License: MIT
Project-URL: Homepage, https://github.com/qquartsco-svg/Cognitive_Kernel
Project-URL: Documentation, https://github.com/qquartsco-svg/Cognitive_Kernel#readme
Project-URL: Repository, https://github.com/qquartsco-svg/Cognitive_Kernel
Project-URL: Issues, https://github.com/qquartsco-svg/Cognitive_Kernel/issues
Keywords: cognitive,memory,ai,agent,long-term-memory,pagerank,decision-making,brain,neuroscience,llm,langchain
Classifier: Development Status :: 4 - Beta
Classifier: Intended Audience :: Developers
Classifier: Intended Audience :: Science/Research
Classifier: License :: OSI Approved :: MIT License
Classifier: Operating System :: OS Independent
Classifier: Programming Language :: Python :: 3
Classifier: Programming Language :: Python :: 3.8
Classifier: Programming Language :: Python :: 3.9
Classifier: Programming Language :: Python :: 3.10
Classifier: Programming Language :: Python :: 3.11
Classifier: Programming Language :: Python :: 3.12
Classifier: Topic :: Scientific/Engineering :: Artificial Intelligence
Classifier: Topic :: Software Development :: Libraries :: Python Modules
Requires-Python: >=3.8
License-File: LICENSE
Requires-Dist: numpy>=1.20.0
Provides-Extra: dev
Requires-Dist: pytest>=7.0; extra == "dev"
Requires-Dist: pytest-cov>=4.0; extra == "dev"
Requires-Dist: black>=23.0; extra == "dev"
Requires-Dist: isort>=5.0; extra == "dev"
Requires-Dist: mypy>=1.0; extra == "dev"
Provides-Extra: langchain
Requires-Dist: langchain>=0.1.0; extra == "langchain"
Provides-Extra: llamaindex
Requires-Dist: llama-index>=0.9.0; extra == "llamaindex"
Provides-Extra: vector
Requires-Dist: chromadb>=0.4.0; extra == "vector"
Requires-Dist: faiss-cpu>=1.7.0; extra == "vector"
Requires-Dist: sentence-transformers>=2.2.0; extra == "vector"
Provides-Extra: all
Requires-Dist: cognitive-kernel[dev,langchain,llamaindex,vector]; extra == "all"
Dynamic: license-file
